dscmailer/__init__.py
dscmailer/mailer.py
dsc_mailer-1.0.1.dist-info/LICENSE
dsc_mailer-1.0.1.dist-info/METADATA
dsc_mailer-1.0.1.dist-info/WHEEL
dsc_mailer-1.0.1.dist-info/top_level.txt
dsc_mailer-1.0.1.dist-info/RECORD
