Metadata-Version: 2.1
Name: dsc-mailer
Version: 1.0.1
Summary: A simple mailing library for python powered applications using Sendgrid.
Home-page: https://github.com/jkuatdsc/dsc-mailer
Author: Victor Waichigo
Author-email: waichigovick@gmail.com
License: MIT
Download-URL: https://github.com/jkuatdsc/dsc-mailer.git
Platform: UNKNOWN
Classifier: License :: OSI Approved :: MIT License
Classifier: Programming Language :: Python :: 3
Classifier: Programming Language :: Python :: 3.7
Requires-Dist: python-decouple
Requires-Dist: sendgrid
